Workbook
Name Aporte: APP!$D$17
Name Patrimonio: APP!$D$20
Name Qtd_Anos: APP!$D$18
Name Rendimento_carteira: APP!$D$13
Name Salario: APP!$D$12
Name Sugestao_investimento: APP!$D$14
Name Taxa_Mensal: APP!$D$19

Sheet APP
B11: CONFIGURAÇÕES
B12: Salário | D12: 2000
B13: Rendiemnto da carteira | D13: 0.006
B14: Sugestão de investimento (30%) | D14: =D12*30% -> 600
B16: INVESTIMENTO MENSAL
B17: Quanto investir por mês? | D17: 200
B18: Por quantos anos? | D18: 10
B19: Taxa de rendedimento mensal? | D19: 0.01079
B20: Patrimônio acumulado ? | D20: =FV(Taxa_Mensal,Qtd_Anos*12,Aporte*-1) -> 48656.843
B21: Dividendo mensais? | D21: =Patrimonio*Rendimento_carteira -> 291.94106
B23: Cenários | D23: Dividendo
A24: 2 | B24: Quanto em 2 Anos? | C24: =FV($D$19,$A24*12,$D$17*-1) -> 5445.5255 | D24: =C24*Rendimento_carteira -> 32.673153
A25: 5 | B25: Quanto em 5 Anos? | C25: =FV($D$19,$A25*12,$D$17*-1) -> 16755.383 | D25: =C25*Rendimento_carteira -> 100.5323
A26: 10 | B26: Quanto em 10 Anos? | C26: =FV($D$19,$A26*12,$D$17*-1) -> 48656.843 | D26: =C26*Rendimento_carteira -> 291.94106
A27: 20 | B27: Quanto em 20 Anos? | C27: =FV($D$19,$A27*12,$D$17*-1) -> 225039.68 | D27: =C27*Rendimento_carteira -> 1350.2381
A28: 30 | B28: Quanto em 30 Anos? | C28: =FV($D$19,$A28*12,$D$17*-1) -> 864433.93 | D28: =C28*Rendimento_carteira -> 5186.6036
B30: PERFIL | C30: Agressivo
B31: VALOR A SER INVESTIDO POR MÊS | C31: =Aporte -> 200
B33: TIPO DE FII | C33: Percentual sugerido | D33: Valores
B34: PAPEL | C34: =VLOOKUP($C$30&"-"&B34,TB!A:D,4,0) -> 0.5 | D34: =C34*$C$31 -> 100
B35: TIJOLO | C35: =VLOOKUP($C$30&"-"&B35,TB!A:D,4,0) -> 0.1 | D35: =C35*$C$31 -> 20
B36: HÍDRIDOS | C36: =VLOOKUP($C$30&"-"&B36,TB!A:D,4,0) -> 0.05 | D36: =C36*$C$31 -> 10
B37: FOFS | C37: =VLOOKUP($C$30&"-"&B37,TB!A:D,4,0) -> 0.05 | D37: =C37*$C$31 -> 10
B38: DESENVOLVIMENTO | C38: =VLOOKUP($C$30&"-"&B38,TB!A:D,4,0) -> 0.2 | D38: =C38*$C$31 -> 40
B39: HOTELARIAS | C39: =VLOOKUP($C$30&"-"&B39,TB!A:D,4,0) -> 0.1 | D39: =C39*$C$31 -> 20
D40: =SUM(D34:D39) -> 200
B58: PARA QUE | C58: Necessidades
B59: VALOR A SER INVESTIDO POR MÊS | C59: =Aporte -> 200
B61: MOTIVO | C61: Percentual sugerido | D61: Valores
B62: Aluguel/hipoteca | C62: =IFERROR(VLOOKUP($C$58&"-"&B62,TB!A25:D34,4,0),0%) -> 0.5 | D62: =C62*$C$59 -> 100
B63: Mantimentos/Transporte | C63: =IFERROR(VLOOKUP($C$58&"-"&B63,TB!A26:D35,4,0),0%) -> 0.3 | D63: =C63*$C$59 -> 60
B64: Contas | C64: =IFERROR(VLOOKUP($C$58&"-"&B64,TB!A27:D36,4,0),0%) -> 0.2 | D64: =C64*$C$59 -> 40
B65: Compras | C65: =IFERROR(VLOOKUP($C$58&"-"&B65,TB!A28:D37,4,0),0%) -> 0 | D65: =C65*$C$59 -> 0
B66: Entretenimento | C66: =IFERROR(VLOOKUP($C$58&"-"&B66,TB!A29:D38,4,0),0%) -> 0 | D66: =C66*$C$59 -> 0
B67: Hobbies | C67: =IFERROR(VLOOKUP($C$58&"-"&B67,TB!A30:D39,4,0),0%) -> 0 | D67: =C67*$C$59 -> 0
B68: Mínima | C68: =IFERROR(VLOOKUP($C$58&"-"&B68,TB!A31:D40,4,0),0%) -> 0 | D68: =C68*$C$59 -> 0
B69: Média | C69: =IFERROR(VLOOKUP($C$58&"-"&B69,TB!A32:D41,4,0),0%) -> 0 | D69: =C69*$C$59 -> 0
B70: Máxima | C70: =IFERROR(VLOOKUP($C$58&"-"&B70,TB!A33:D42,4,0),0%) -> 0 | D70: =C70*$C$59 -> 0
D71: =SUM(D62:D70) -> 200

Sheet TB
A3: CHAVE | B3: PERFIL | C3: TIPO FII | D3: % | H3: %
A4: =$B$5&"-"&C4 -> Conservador-PAPEL | B4: Conservador | C4: PAPEL | D4: 0.3 | G4: Moderado-TIJOLO | H4: =VLOOKUP(G4,$A:$D,4,0) -> 0.35
A5: =$B$5&"-"&C5 -> Conservador-TIJOLO | B5: Conservador | C5: TIJOLO | D5: 0.5
A6: =$B$5&"-"&C6 -> Conservador-HÍDRIDOS | B6: Conservador | C6: HÍDRIDOS | D6: 0.1
A7: =$B$5&"-"&C7 -> Conservador-FOFS | B7: Conservador | C7: FOFS | D7: 0.1
A8: =$B$5&"-"&C8 -> Conservador-DESENVOLVIMENTO | B8: Conservador | C8: DESENVOLVIMENTO | D8: 0
A9: =$B$5&"-"&C9 -> Conservador-HOTELARIAS | B9: Conservador | C9: HOTELARIAS | D9: 0
A10: =$B$10&"-"&C10 -> Moderado-PAPEL | B10: Moderado | C10: PAPEL | D10: 0.32
A11: =$B$10&"-"&C11 -> Moderado-TIJOLO | B11: Moderado | C11: TIJOLO | D11: 0.35
A12: =$B$10&"-"&C12 -> Moderado-HÍDRIDOS | B12: Moderado | C12: HÍDRIDOS | D12: 0.08
A13: =$B$10&"-"&C13 -> Moderado-FOFS | B13: Moderado | C13: FOFS | D13: 0.05
A14: =$B$10&"-"&C14 -> Moderado-DESENVOLVIMENTO | B14: Moderado | C14: DESENVOLVIMENTO | D14: 0.1
A15: =$B$10&"-"&C15 -> Moderado-HOTELARIAS | B15: Moderado | C15: HOTELARIAS | D15: 0.1
A16: =$B$16&"-"&C16 -> Agressivo-PAPEL | B16: Agressivo | C16: PAPEL | D16: 0.5
A17: =$B$16&"-"&C17 -> Agressivo-TIJOLO | B17: Agressivo | C17: TIJOLO | D17: 0.1
A18: =$B$16&"-"&C18 -> Agressivo-HÍDRIDOS | B18: Agressivo | C18: HÍDRIDOS | D18: 0.05
A19: =$B$16&"-"&C19 -> Agressivo-FOFS | B19: Agressivo | C19: FOFS | D19: 0.05
A20: =$B$16&"-"&C20 -> Agressivo-DESENVOLVIMENTO | B20: Agressivo | C20: DESENVOLVIMENTO | D20: 0.2
A21: =$B$16&"-"&C21 -> Agressivo-HOTELARIAS | B21: Agressivo | C21: HOTELARIAS | D21: 0.1
A25: SUGESTÃO | B25: PARA QUE | C25: MOTIVO | D25: %
A26: =$B26&"-"&C26 -> Necessidades-Aluguel/hipoteca | B26: Necessidades | C26: Aluguel/hipoteca | D26: 0.5
A27: =$B27&"-"&C27 -> Necessidades-Mantimentos/Transporte | B27: Necessidades | C27: Mantimentos/Transporte | D27: 0.3
A28: =$B28&"-"&C28 -> Necessidades-Contas | B28: Necessidades | C28: Contas | D28: 0.2
A29: =$B29&"-"&C29 -> Desejos-Compras | B29: Desejos | C29: Compras | D29: 0.34
A30: =$B30&"-"&C30 -> Desejos-Entretenimento | B30: Desejos | C30: Entretenimento | D30: 0.33
A31: =$B31&"-"&C31 -> Desejos-Hobbies | B31: Desejos | C31: Hobbies | D31: 0.33
A32: =$B32&"-"&C32 -> Economias-Mínima | B32: Economias | C32: Mínima | D32: 0.2
A33: =$B33&"-"&C33 -> Economias-Média | B33: Economias | C33: Média | D33: 0.3
A34: =$B34&"-"&C34 -> Economias-Máxima | B34: Economias | C34: Máxima | D34: 0.5
